LICENSE
README.md
setup.cfg
setup.py
tests/__init__.py
tests/structure_factor.py
tests/plugin/__init__.py
tests/plugin/scaling/__init__.py
tests/plugin/scaling/scale.py
tests/plugin/stress/__init__.py
tests/plugin/stress/test_fit_twopeaks.py
uxdconverter/__init__.py
uxdconverter/compare.py
uxdconverter/converter.py
uxdconverter/enums.py
uxdconverter/exporter.py
uxdconverter/fwhm.py
uxdconverter/generalparser.py
uxdconverter/main.py
uxdconverter/measurement.py
uxdconverter/operation.py
uxdconverter/util.py
uxdconverter.egg-info/PKG-INFO
uxdconverter.egg-info/SOURCES.txt
uxdconverter.egg-info/dependency_links.txt
uxdconverter.egg-info/requires.txt
uxdconverter.egg-info/top_level.txt
uxdconverter/constants/__init__.py
uxdconverter/constants/atomic_scattering_factor.py
uxdconverter/constants/data/atomic_form_factor_approximation.dat
uxdconverter/diffraction/__init__.py
uxdconverter/diffraction/crystal.py
uxdconverter/diffraction/structurefactor.py
uxdconverter/diffraction/unitcell.py
uxdconverter/export/__init__.py
uxdconverter/export/orso.py
uxdconverter/parser/__init__.py
uxdconverter/parser/general.py
uxdconverter/parser/nicos.py
uxdconverter/parser/raw.py
uxdconverter/parser/simple.py
uxdconverter/parser/uxd.py
uxdconverter/parser/xrdml.py
uxdconverter/parser/ndatautils/__init__.py
uxdconverter/parser/ndatautils/parser.py
uxdconverter/plugin/__init__.py
uxdconverter/plugin/plugins.py
uxdconverter/plugin/stress/__init__.py
uxdconverter/plugin/stress/analysis.py
uxdconverter/plugin/stress/fit.py
uxdconverter/plugin/stress/psi_fit.py
uxdconverter/raw/__init__.py
uxdconverter/raw/converter.py
uxdconverter/raw/data.py
uxdconverter/raw/measurement.py
uxdconverter/raw/parser.py
uxdconverter/raw/header/__init__.py
uxdconverter/raw/header/file.py
uxdconverter/raw/header/range.py
uxdconverter/raw/header/structure.py
uxdconverter/raw/header/supplementary.py
uxdconverter/raw/test/__init__.py
uxdconverter/raw/test/file.py
uxdconverter/transition_energy/__init__.py
uxdconverter/transition_energy/database.py
uxdconverter/transition_energy/nist-energy-database.dat
uxdconverter/ui/__init__.py
uxdconverter/ui/controller.py
uxdconverter/ui/graph.py
