Metadata-Version: 2.1
Name: uxdconverter
Version: 1.1.1
Summary: UXDConverter
Home-page: https://github.com/TUM-E21-ThinFilms/UXDConverter
Author: Alexander Book
Author-email: alexander.book@frm2.tum.de
License: GNU General Public License (GPL), Version 3
Platform: UNKNOWN
License-File: LICENSE
